{"trial_id": "5115ff9b9eac47816552b339b6ee80ca", "hyperparameters": {"space": [{"class_name": "Float", "config": {"name": "elastic_lambda_l1", "default": 0.0001, "conditions": [], "min_value": 0.0001, "max_value": 0.01, "step": null, "sampling": null}}, {"class_name": "Float", "config": {"name": "elastic_lambda_l2", "default": 0.0001, "conditions": [], "min_value": 0.0001, "max_value": 0.01, "step": null, "sampling": null}}, {"class_name": "Float", "config": {"name": "elastic_lambda_l3", "default": 0.0001, "conditions": [], "min_value": 0.0001, "max_value": 0.01, "step": null, "sampling": null}}, {"class_name": "Float", "config": {"name": "elastic_lambda_l4", "default": 0.0001, "conditions": [], "min_value": 0.0001, "max_value": 0.01, "step": null, "sampling": null}}, {"class_name": "Int", "config": {"name": "units_l1", "default": 21, "conditions": [], "min_value": 21, "max_value": 42, "step": 4, "sampling": null}}, {"class_name": "Int", "config": {"name": "units_l2", "default": 21, "conditions": [], "min_value": 21, "max_value": 42, "step": 4, "sampling": null}}, {"class_name": "Int", "config": {"name": "units_l3", "default": 21, "conditions": [], "min_value": 21, "max_value": 42, "step": 4, "sampling": null}}, {"class_name": "Choice", "config": {"name": "lr", "default": 0.01, "conditions": [], "values": [0.01, 0.001, 0.0001], "ordered": true}}], "values": {"elastic_lambda_l1": 0.001425391699758723, "elastic_lambda_l2": 0.0019076506345733872, "elastic_lambda_l3": 0.004355416347646651, "elastic_lambda_l4": 0.00641354756695107, "units_l1": 25, "units_l2": 21, "units_l3": 33, "lr": 0.001}}, "metrics": {"metrics": {"loss": {"direction": "min", "observations": [{"value": [1.0394294261932373], "step": 0}]}, "accuracy": {"direction": "max", "observations": [{"value": [0.49369367957115173], "step": 0}]}, "val_loss": {"direction": "min", "observations": [{"value": [1.1138312816619873], "step": 0}]}, "val_accuracy": {"direction": "max", "observations": [{"value": [0.48235294222831726], "step": 0}]}}}, "score": 1.1138312816619873, "best_step": 0, "status": "COMPLETED"}